odoo/addons/project_task_report/README.rst
odoo/addons/project_task_report/__init__.py
odoo/addons/project_task_report/__manifest__.py
odoo/addons/project_task_report/i18n/es.po
odoo/addons/project_task_report/i18n/fr.po
odoo/addons/project_task_report/i18n/hr.po
odoo/addons/project_task_report/i18n/project_task_report.pot
odoo/addons/project_task_report/i18n/sl.po
odoo/addons/project_task_report/readme/CONTRIBUTORS.rst
odoo/addons/project_task_report/readme/DESCRIPTION.rst
odoo/addons/project_task_report/readme/USAGE.rst
odoo/addons/project_task_report/static/description/icon.png
odoo/addons/project_task_report/static/description/index.html
odoo/addons/project_task_report/views/project_task_chatter_report.xml
odoo/addons/project_task_report/views/project_task_report.xml
odoo13_addon_project_task_report-13.0.1.0.1.dev3.dist-info/METADATA
odoo13_addon_project_task_report-13.0.1.0.1.dev3.dist-info/WHEEL
odoo13_addon_project_task_report-13.0.1.0.1.dev3.dist-info/top_level.txt
odoo13_addon_project_task_report-13.0.1.0.1.dev3.dist-info/RECORD
